aclinks/__init__.py
aclinks/__main__.py
aclinks/checker.py
awesome_check_link-0.1.6.dist-info/LICENSE
awesome_check_link-0.1.6.dist-info/METADATA
awesome_check_link-0.1.6.dist-info/WHEEL
awesome_check_link-0.1.6.dist-info/entry_points.txt
awesome_check_link-0.1.6.dist-info/top_level.txt
awesome_check_link-0.1.6.dist-info/RECORD
