Metadata-Version: 2.1
Name: awesome-check-link
Version: 0.1.6
Summary: Check if links in md file and more particuraly in awesome-list are down or not.
Home-page: https://github.com/remiflavien1/awesome-check-link
Author: shadawck
Author-email: hug211mire@gmail.com
License: MIT
Keywords: awesome-check-link,awesome,awesome list,checker,down,link checker
Platform: UNKNOWN
Classifier: Topic :: Software Development :: Libraries :: Python Modules
Classifier: Programming Language :: Python :: 3
Classifier: Programming Language :: Python :: Implementation :: PyPy
Classifier: Topic :: Software Development :: Libraries :: Python Modules
Classifier: License :: OSI Approved :: MIT License
Requires-Dist: requests
Requires-Dist: docopt
